homepage2vec/__init__.py
homepage2vec/data_collection.py
homepage2vec/model.py
homepage2vec/model_loader.py
homepage2vec/textual_extractor.py
homepage2vec/visual_extractor.py
homepage2vec-0.0.3rc1.dist-info/LICENSE
homepage2vec-0.0.3rc1.dist-info/METADATA
homepage2vec-0.0.3rc1.dist-info/WHEEL
homepage2vec-0.0.3rc1.dist-info/top_level.txt
homepage2vec-0.0.3rc1.dist-info/RECORD
