Metadata-Version: 2.1
Name: homepage2vec
Version: 0.0.3rc1
Summary: Language-Agnostic Website Embedding and Classification
Home-page: https://github.com/epfl-dlab/Homepage2vec
Author: Tiziano Piccardi
Author-email: tiziano.piccardi@epfl.ch
Project-URL: Bug Tracker, https://github.com/epfl-dlab/Homepage2vec/issues
Classifier: Programming Language :: Python :: 3
Classifier: License :: OSI Approved :: MIT License
Classifier: Operating System :: OS Independent
Requires-Python: >=3.6
License-File: LICENSE
Requires-Dist: torch (>=1.13.0)
Requires-Dist: torchvision (>=0.14.0)
Requires-Dist: beautifulsoup4 (>=4.11.1)
Requires-Dist: sentence-transformers (>=2.2.2)
Requires-Dist: lxml (>=4.9.1)
Provides-Extra: visual
Requires-Dist: selenium (>=4.6.1) ; extra == 'visual'
